{
  "variable": {
    "instance_id": [
      {
        "description": "The unique identifier for the Amazon Connect instance.",
        "nullable": false,
        "type": "string"
      }
    ],
    "hours_of_operation_id": [
      {
        "description": "The unique identifier for the hours of operation configuration. If not provided, a new configuration will be created.",
        "nullable": true,
        "type": "string"
      }
    ],
    "name": [
      {
        "description": "The name of the hours of operation configuration.",
        "nullable": true,
        "type": "string"
      }
    ]
  }
}